wati_mcp/__init__.py
wati_mcp/server.py
wati_mcp_server-0.1.1.dist-info/licenses/LICENSE
wati_mcp_server-0.1.1.dist-info/METADATA
wati_mcp_server-0.1.1.dist-info/WHEEL
wati_mcp_server-0.1.1.dist-info/entry_points.txt
wati_mcp_server-0.1.1.dist-info/top_level.txt
wati_mcp_server-0.1.1.dist-info/RECORD
