Metadata-Version: 2.4
Name: wati-mcp-server
Version: 0.1.1
Summary: MCP Server for WATI WhatsApp Business API integration
Author-email: Jairaj Mehra <jairajmehra98@gmail.com>
Maintainer-email: Jairaj Mehra <jairajmehra98@gmail.com>
License-Expression: MIT
Project-URL: Homepage, https://github.com/Jairajmehra/wati_whatsapp_mcp
Project-URL: Documentation, https://github.com/Jairajmehra/wati_whatsapp_mcp#readme
Project-URL: Repository, https://github.com/Jairajmehra/wati_whatsapp_mcp.git
Project-URL: Issues, https://github.com/Jairajmehra/wati_whatsapp_mcp/issues
Keywords: mcp,whatsapp,wati,business-api,model-context-protocol,chatbot,messaging
Classifier: Development Status :: 4 - Beta
Classifier: Intended Audience :: Developers
Classifier: Operating System :: OS Independent
Classifier: Programming Language :: Python :: 3
Classifier: Programming Language :: Python :: 3.8
Classifier: Programming Language :: Python :: 3.9
Classifier: Programming Language :: Python :: 3.10
Classifier: Programming Language :: Python :: 3.11
Classifier: Programming Language :: Python :: 3.12
Classifier: Topic :: Communications :: Chat
Classifier: Topic :: Software Development :: Libraries :: Python Modules
Requires-Python: >=3.8
License-File: LICENSE
Requires-Dist: mcp>=1.0.0
Requires-Dist: requests>=2.25.0
Requires-Dist: python-dotenv>=0.19.0
Provides-Extra: dev
Requires-Dist: pytest>=7.0.0; extra == "dev"
Requires-Dist: pytest-cov>=4.0.0; extra == "dev"
Requires-Dist: black>=22.0.0; extra == "dev"
Requires-Dist: flake8>=5.0.0; extra == "dev"
Requires-Dist: mypy>=1.0.0; extra == "dev"
Requires-Dist: pre-commit>=2.20.0; extra == "dev"
Dynamic: license-file
